dash_customizable_app_style/__init__.py
dash_customizable_app_style-0.0.7.dist-info/METADATA
dash_customizable_app_style-0.0.7.dist-info/WHEEL
dash_customizable_app_style-0.0.7.dist-info/entry_points.txt
dash_customizable_app_style-0.0.7.dist-info/top_level.txt
dash_customizable_app_style-0.0.7.dist-info/RECORD
