Metadata-Version: 2.4
Name: dash_customizable_app_style
Version: 0.0.7
Summary: Customizable background color, text color and font family for Dash applications using Dash Hooks
Home-page: https://github.com/XLlobet/dash-customizable-app-style
Author: X.Llobet
Author-email: "X.Llobet" <llbt.nvs.x@gmail.com>
Requires-Python: >=3.8
Requires-Dist: dash>=3.0.0
Requires-Dist: dash-bootstrap-components==2.0.3
Dynamic: author
Dynamic: home-page
